{
  "activities": [
    {
      "message": "New reply in \"Run command get-service and include the ...\"",
      "time": "Just now",
      "type": "reply",
      "color": "bg-purple-500"
    },
    {
      "message": "3 new topics this week",
      "time": "This week",
      "type": "stats",
      "color": "bg-green-500"
    },
    {
      "message": "Active PowerShell discussions ongoing",
      "time": "Ongoing",
      "type": "community",
      "color": "bg-blue-500"
    }
  ],
  "stats": {
    "total_topics": 19360,
    "total_posts": 118072,
    "active_users": 9576,
    "topics_this_week": 3
  },
  "last_updated": "2026-05-15T16:41:04.631Z"
}