{
  "activities": [
    {
      "message": "New reply in \"Windows Terminal - Memory Usage...\"",
      "time": "1 hours ago",
      "type": "reply",
      "color": "bg-purple-500"
    },
    {
      "message": "2 new topics this week",
      "time": "This week",
      "type": "stats",
      "color": "bg-green-500"
    },
    {
      "message": "Active PowerShell discussions ongoing",
      "time": "Ongoing",
      "type": "community",
      "color": "bg-blue-500"
    }
  ],
  "stats": {
    "total_topics": 19302,
    "total_posts": 117596,
    "active_users": 9621,
    "topics_this_week": 2
  },
  "last_updated": "2025-10-15T08:10:10.778Z"
}